[
  {
    "anonymous": false,
    "inputs": [
      {
        "indexed": false,
        "internalType": "uint24",
        "name": "newLower",
        "type": "uint24"
      },
      {
        "indexed": false,
        "internalType": "uint24",
        "name": "newUpper",
        "type": "uint24"
      },
      {
        "indexed": false,
        "internalType": "uint24",
        "name": "desiredActiveId",
        "type": "uint24"
      },
      {
        "indexed": false,
        "internalType": "uint24",
        "name": "slippageActiveId",
        "type": "uint24"
      },
      {
        "indexed": false,
        "internalType": "uint256",
        "name": "amountX",
        "type": "uint256"
      },
      {
        "indexed": false,
        "internalType": "uint256",
        "name": "amountY",
        "type": "uint256"
      }
    ],
    "name": "RebalanceStart",
    "type": "event"
  }
]